consoleCanvas/__init__.py
ConsoleCanvas-0.0.5.dist-info/METADATA
ConsoleCanvas-0.0.5.dist-info/WHEEL
ConsoleCanvas-0.0.5.dist-info/top_level.txt
ConsoleCanvas-0.0.5.dist-info/RECORD
