Metadata-Version: 2.1
Name: ConsoleCanvas
Version: 0.0.5
Summary: 终端画布
Home-page: UNKNOWN
Author: 1019157263@qq.com
Author-email: 1019157263@qq.com
License: MIT
Platform: UNKNOWN
Classifier: Programming Language :: Python :: 3
Classifier: License :: OSI Approved :: MIT License
Classifier: Operating System :: OS Independent
